mapas/__init__.py
mapas/layer.py
mapas/map.py
mapas/renderer.py
mapas/tiles.py
mapas/vector.py
mapas/version.txt
mapas/source/__init__.py
mapas/source/base.py
mapas/source/image_wms.py
mapas/source/mapbox.py
tests/__init__.py
tests/api_test.py
tests/testutils.py
tests/tile_test.py
tests/tiles_test.py
mapas-1.3.1.dist-info/METADATA
mapas-1.3.1.dist-info/WHEEL
mapas-1.3.1.dist-info/entry_points.txt
mapas-1.3.1.dist-info/top_level.txt
mapas-1.3.1.dist-info/RECORD
