Metadata-Version: 2.1
Name: mapas
Version: 1.3.1
Summary: Create static maps from different layers
Home-page: https://gitlab.com/categulario/mapas-py
Author: Abraham Toriz Cruz
Author-email: categulario@gmail.com
License: GPLv3
Keywords: map,mapa,static map
Platform: UNKNOWN
Classifier: Development Status :: 4 - Beta
Classifier: Intended Audience :: Developers
Classifier: Topic :: Software Development :: Libraries :: Python Modules
Classifier: License :: OSI Approved :: GNU General Public License v3 (GPLv3)
Classifier: Programming Language :: Python :: 3
Classifier: Programming Language :: Python :: 3.5
Classifier: Programming Language :: Python :: 3.6
Classifier: Programming Language :: Python :: 3.7
Classifier: Programming Language :: Python :: 3.8
Classifier: Programming Language :: Python :: 3.9
Requires-Dist: requests
Requires-Dist: Pillow (>=7.0.0)
